yosafe_packages/yosafe_subpackage_1/__init__.py
yosafe_packages/yosafe_subpackage_1/yosafe_subpackage_1_functions.py
yosafe_packages/yosafe_subpackage_1/yosafe_subpackage_1_functions_2.py
yosafe_packages/yosafe_subpackage_2/__init__.py
yosafe_packages/yosafe_subpackage_2/yosafe_subpackage_2_functions.py
yosafe_packages/yosafe_subpackage_3/__init__.py
yosafe_packages/yosafe_subpackage_3/yosafe_subpackage_3_functions.py
yosafe_packages-0.11.22.dist-info/METADATA
yosafe_packages-0.11.22.dist-info/WHEEL
yosafe_packages-0.11.22.dist-info/RECORD
