Metadata-Version: 2.1
Name: yosafe-packages
Version: 0.11.22
Summary: 
Author: Yo581515
Author-email: 581515@stud.hvl.no
Requires-Python: >=3.12,<4.0.0
Classifier: Programming Language :: Python :: 3
Classifier: Programming Language :: Python :: 3.12
Requires-Dist: numpy (>=2.1.1,<3.0.0)
Requires-Dist: pydantic (>=2.9.1,<3.0.0)
Requires-Dist: pytest (>=8.3.2,<9.0.0)
Requires-Dist: requests (>=2.32.3,<3.0.0)
Requires-Dist: typing-extensions (>=4.6.3,<5.0.0)
